Workbook

Sheet ReadMe
A1: Well Economics & NPV/IRR Calculator
A3: Purpose:
A4: This tool models the 5-year cash flow of a single oil well and calculates its Net Present Value (NPV) and Internal Rate of Return (IRR), the two standard metrics used to evaluate whether a well is economically worth drilling.
A6: How it works:
A7: 1. Inputs tab holds all assumptions (price, costs, decline rate, etc.)
A8: 2. Cash Flow Model tab forecasts monthly oil production using Arps exponential decline, converts it to revenue, subtracts royalties and operating costs, and calculates monthly net cash flow.
A9: 3. NPV and IRR are calculated from that cash flow at the bottom of the Cash Flow Model tab.
A10: 4. Sensitivity tab shows how NPV changes across different oil price and CapEx scenarios using a Data Table.
A12: Author: Nahil Nigar
A14: This tool was built with guidance from Claude (Anthropic's AI assistant),
A15: which was used as a learning aid to understand the underlying formulas,
A16: Excel functions, and the Solver-alternative approach used here. The
... A19: numbers.

Sheet Inputs
A1: WELL ECONOMICS — INPUT ASSUMPTIONS
A3: CapEx ($) | B3: 7000000
A4: OpEx per Month ($) | B4: 15000
A5: Oil Price ($/bbl) | B5: 75
A6: Royalty Rate (%) | B6: 0.1875
A7: Initial Rate qi (bbl/day) | B7: 500
A8: Initial Decline Rate Di (annual, %) | B8: 0.35
A9: Discount Rate (%) | B9: 0.1

Sheet Cash Flow Model
A1: Month # | B1: Date | C1: Production (bbl/day) | D1: Monthly Production (bbl) | E1: Gross Revenue | F1: Royalty ($) | G1: Net Revenue ($) | H1: OpEx ($) | I1: Net Cash Flow ($)
A2: 0 | B2: 46388 | C2: =Inputs!$B$7*EXP(-Inputs!$B$8*(A2/12)) -> 500 | D2: =C2*30.4 -> 15200 | E2: =D2*Inputs!$B$5 -> 1140000 | F2: =E2*Inputs!$B$6 -> 213750 | G2: =E2-F2 -> 926250 | H2: =IF(A2=0,0,Inputs!$B$4) -> 0 | I2: =IF(A2=0,-Inputs!$B$3,G2-H2) -> -7000000
A3: 1 | B3: 46419 | C3: =Inputs!$B$7*EXP(-Inputs!$B$8*(A3/12)) -> 485.62729 | D3: =C3*30.4 -> 14763.07 | E3: =D3*Inputs!$B$5 -> 1107230.2 | F3: =E3*Inputs!$B$6 -> 207605.67 | G3: =E3-F3 -> 899624.55 | H3: =IF(A3=0,0,Inputs!$B$4) -> 15000 | I3: =IF(A3=0,-Inputs!$B$3,G3-H3) -> 884624.55
A4: 2 | B4: 46447 | C4: =Inputs!$B$7*EXP(-Inputs!$B$8*(A4/12)) -> 471.66772 | D4: =C4*30.4 -> 14338.699 | E4: =D4*Inputs!$B$5 -> 1075402.4 | F4: =E4*Inputs!$B$6 -> 201637.95 | G4: =E4-F4 -> 873764.46 | H4: =IF(A4=0,0,Inputs!$B$4) -> 15000 | I4: =IF(A4=0,-Inputs!$B$3,G4-H4) -> 858764.46
A5: 3 | B5: 46478 | C5: =Inputs!$B$7*EXP(-Inputs!$B$8*(A5/12)) -> 458.10944 | D5: =C5*30.4 -> 13926.527 | E5: =D5*Inputs!$B$5 -> 1044489.5 | F5: =E5*Inputs!$B$6 -> 195841.78 | G5: =E5-F5 -> 848647.73 | H5: =IF(A5=0,0,Inputs!$B$4) -> 15000 | I5: =IF(A5=0,-Inputs!$B$3,G5-H5) -> 833647.73
A6: 4 | B6: 46508 | C6: =Inputs!$B$7*EXP(-Inputs!$B$8*(A6/12)) -> 444.94089 | D6: =C6*30.4 -> 13526.203 | E6: =D6*Inputs!$B$5 -> 1014465.2 | F6: =E6*Inputs!$B$6 -> 190212.23 | G6: =E6-F6 -> 824252.99 | H6: =IF(A6=0,0,Inputs!$B$4) -> 15000 | I6: =IF(A6=0,-Inputs!$B$3,G6-H6) -> 809252.99
A7: 5 | B7: 46539 | C7: =Inputs!$B$7*EXP(-Inputs!$B$8*(A7/12)) -> 432.15087 | D7: =C7*30.4 -> 13137.386 | E7: =D7*Inputs!$B$5 -> 985303.99 | F7: =E7*Inputs!$B$6 -> 184744.5 | G7: =E7-F7 -> 800559.49 | H7: =IF(A7=0,0,Inputs!$B$4) -> 15000 | I7: =IF(A7=0,-Inputs!$B$3,G7-H7) -> 785559.49
A8: 6 | B8: 46569 | C8: =Inputs!$B$7*EXP(-Inputs!$B$8*(A8/12)) -> 419.72851 | D8: =C8*30.4 -> 12759.747 | E8: =D8*Inputs!$B$5 -> 956981 | F8: =E8*Inputs!$B$6 -> 179433.94 | G8: =E8-F8 -> 777547.07 | H8: =IF(A8=0,0,Inputs!$B$4) -> 15000 | I8: =IF(A8=0,-Inputs!$B$3,G8-H8) -> 762547.07
A9: 7 | B9: 46600 | C9: =Inputs!$B$7*EXP(-Inputs!$B$8*(A9/12)) -> 407.66324 | D9: =C9*30.4 -> 12392.962 | E9: =D9*Inputs!$B$5 -> 929472.18 | F9: =E9*Inputs!$B$6 -> 174276.03 | G9: =E9-F9 -> 755196.14 | H9: =IF(A9=0,0,Inputs!$B$4) -> 15000 | I9: =IF(A9=0,-Inputs!$B$3,G9-H9) -> 740196.14
A10: 8 | B10: 46631 | C10: =Inputs!$B$7*EXP(-Inputs!$B$8*(A10/12)) -> 395.94478 | D10: =C10*30.4 -> 12036.721 | E10: =D10*Inputs!$B$5 -> 902754.11 | F10: =E10*Inputs!$B$6 -> 169266.39 | G10: =E10-F10 -> 733487.71 | H10: =IF(A10=0,0,Inputs!$B$4) -> 15000 | I10: =IF(A10=0,-Inputs!$B$3,G10-H10) -> 718487.71
A11: 9 | B11: 46661 | C11: =Inputs!$B$7*EXP(-Inputs!$B$8*(A11/12)) -> 384.56318 | D11: =C11*30.4 -> 11690.721 | E11: =D11*Inputs!$B$5 -> 876804.06 | F11: =E11*Inputs!$B$6 -> 164400.76 | G11: =E11-F11 -> 712403.29 | H11: =IF(A11=0,0,Inputs!$B$4) -> 15000 | I11: =IF(A11=0,-Inputs!$B$3,G11-H11) -> 697403.29
A12: 10 | B12: 46692 | C12: =Inputs!$B$7*EXP(-Inputs!$B$8*(A12/12)) -> 373.50875 | D12: =C12*30.4 -> 11354.666 | E12: =D12*Inputs!$B$5 -> 851599.95 | F12: =E12*Inputs!$B$6 -> 159674.99 | G12: =E12-F12 -> 691924.96 | H12: =IF(A12=0,0,Inputs!$B$4) -> 15000 | I12: =IF(A12=0,-Inputs!$B$3,G12-H12) -> 676924.96
A13: 11 | B13: 46722 | C13: =Inputs!$B$7*EXP(-Inputs!$B$8*(A13/12)) -> 362.77208 | D13: =C13*30.4 -> 11028.271 | E13: =D13*Inputs!$B$5 -> 827120.35 | F13: =E13*Inputs!$B$6 -> 155085.07 | G13: =E13-F13 -> 672035.28 | H13: =IF(A13=0,0,Inputs!$B$4) -> 15000 | I13: =IF(A13=0,-Inputs!$B$3,G13-H13) -> 657035.28
... A62: 60 | B62: 48214 | C62: =Inputs!$B$7*EXP(-Inputs!$B$8*(A62/12)) -> 86.886972 | D62: =C62*30.4 -> 2641.3639 | E62: =D62*Inputs!$B$5 -> 198102.3 | F62: =E62*Inputs!$B$6 -> 37144.18 | G62: =E62-F62 -> 160958.12 | H62: =IF(A62=0,0,Inputs!$B$4) -> 15000 | I62: =IF(A62=0,-Inputs!$B$3,G62-H62) -> 145958.12
A65: NPV ($) | B65: =NPV(Inputs!$B$9/12, I3:I62)+I2 -> 13993996
A66: IRR (%) | B66: =(1+IRR(I2:I62))^12-1 -> 2.0345181

Sheet Sensitivity
B1: NPV Sensitivity: Oil Price vs. CapEx
A3: NPV ($) | B3: 50 | C3: 65 | D3: 75 | E3: 85 | F3: 100
A4: 2000000 | B4: {=-$A4+NPV(Inputs!$B$9,'Cash Flow Model'!$D$3:$D$62*B$3*(1-Inputs!$B$6)-Inputs!$B$4)} -> 2506249.6 | C4: {=-$A4+NPV(Inputs!$B$9,'Cash Flow Model'!$D$3:$D$62*C$3*(1-Inputs!$B$6)-Inputs!$B$4)} -> 3902976.7 | D4: {=-$A4+NPV(Inputs!$B$9,'Cash Flow Model'!$D$3:$D$62*D$3*(1-Inputs!$B$6)-Inputs!$B$4)} -> 4834128.1 | E4: {=-$A4+NPV(Inputs!$B$9,'Cash Flow Model'!$D$3:$D$62*E$3*(1-Inputs!$B$6)-Inputs!$B$4)} -> 5765279.5 | F4: {=-$A4+NPV(Inputs!$B$9,'Cash Flow Model'!$D$3:$D$62*F$3*(1-Inputs!$B$6)-Inputs!$B$4)} -> 7162006.6
A5: 2250000 | B5: {=-$A5+NPV(Inputs!$B$9,'Cash Flow Model'!$D$3:$D$62*B$3*(1-Inputs!$B$6)-Inputs!$B$4)} -> 2256249.6 | C5: {=-$A5+NPV(Inputs!$B$9,'Cash Flow Model'!$D$3:$D$62*C$3*(1-Inputs!$B$6)-Inputs!$B$4)} -> 3652976.7 | D5: {=-$A5+NPV(Inputs!$B$9,'Cash Flow Model'!$D$3:$D$62*D$3*(1-Inputs!$B$6)-Inputs!$B$4)} -> 4584128.1 | E5: {=-$A5+NPV(Inputs!$B$9,'Cash Flow Model'!$D$3:$D$62*E$3*(1-Inputs!$B$6)-Inputs!$B$4)} -> 5515279.5 | F5: {=-$A5+NPV(Inputs!$B$9,'Cash Flow Model'!$D$3:$D$62*F$3*(1-Inputs!$B$6)-Inputs!$B$4)} -> 6912006.6
A6: 2500000 | B6: {=-$A6+NPV(Inputs!$B$9,'Cash Flow Model'!$D$3:$D$62*B$3*(1-Inputs!$B$6)-Inputs!$B$4)} -> 2006249.6 | C6: {=-$A6+NPV(Inputs!$B$9,'Cash Flow Model'!$D$3:$D$62*C$3*(1-Inputs!$B$6)-Inputs!$B$4)} -> 3402976.7 | D6: {=-$A6+NPV(Inputs!$B$9,'Cash Flow Model'!$D$3:$D$62*D$3*(1-Inputs!$B$6)-Inputs!$B$4)} -> 4334128.1 | E6: {=-$A6+NPV(Inputs!$B$9,'Cash Flow Model'!$D$3:$D$62*E$3*(1-Inputs!$B$6)-Inputs!$B$4)} -> 5265279.5 | F6: {=-$A6+NPV(Inputs!$B$9,'Cash Flow Model'!$D$3:$D$62*F$3*(1-Inputs!$B$6)-Inputs!$B$4)} -> 6662006.6
A7: 2750000 | B7: {=-$A7+NPV(Inputs!$B$9,'Cash Flow Model'!$D$3:$D$62*B$3*(1-Inputs!$B$6)-Inputs!$B$4)} -> 1756249.6 | C7: {=-$A7+NPV(Inputs!$B$9,'Cash Flow Model'!$D$3:$D$62*C$3*(1-Inputs!$B$6)-Inputs!$B$4)} -> 3152976.7 | D7: {=-$A7+NPV(Inputs!$B$9,'Cash Flow Model'!$D$3:$D$62*D$3*(1-Inputs!$B$6)-Inputs!$B$4)} -> 4084128.1 | E7: {=-$A7+NPV(Inputs!$B$9,'Cash Flow Model'!$D$3:$D$62*E$3*(1-Inputs!$B$6)-Inputs!$B$4)} -> 5015279.5 | F7: {=-$A7+NPV(Inputs!$B$9,'Cash Flow Model'!$D$3:$D$62*F$3*(1-Inputs!$B$6)-Inputs!$B$4)} -> 6412006.6
A8: 3000000 | B8: {=-$A8+NPV(Inputs!$B$9,'Cash Flow Model'!$D$3:$D$62*B$3*(1-Inputs!$B$6)-Inputs!$B$4)} -> 1506249.6 | C8: {=-$A8+NPV(Inputs!$B$9,'Cash Flow Model'!$D$3:$D$62*C$3*(1-Inputs!$B$6)-Inputs!$B$4)} -> 2902976.7 | D8: {=-$A8+NPV(Inputs!$B$9,'Cash Flow Model'!$D$3:$D$62*D$3*(1-Inputs!$B$6)-Inputs!$B$4)} -> 3834128.1 | E8: {=-$A8+NPV(Inputs!$B$9,'Cash Flow Model'!$D$3:$D$62*E$3*(1-Inputs!$B$6)-Inputs!$B$4)} -> 4765279.5 | F8: {=-$A8+NPV(Inputs!$B$9,'Cash Flow Model'!$D$3:$D$62*F$3*(1-Inputs!$B$6)-Inputs!$B$4)} -> 6162006.6
